boil_an_egg/__init__.py
boil_an_egg/utils.py
boil_an_egg-1.2.3.dist-info/METADATA
boil_an_egg-1.2.3.dist-info/WHEEL
boil_an_egg-1.2.3.dist-info/licenses/LICENSE
boil_an_egg-1.2.3.dist-info/RECORD
